esy/osm/pbf/__init__.py
esy/osm/pbf/file.py
esy/osm/pbf/fileformat_pb2.py
esy/osm/pbf/index.py
esy/osm/pbf/osmformat_pb2.py
esy/osm/pbf/test.py
esy_osm_pbf-0.1.1.dist-info/LICENSE
esy_osm_pbf-0.1.1.dist-info/METADATA
esy_osm_pbf-0.1.1.dist-info/WHEEL
esy_osm_pbf-0.1.1.dist-info/top_level.txt
esy_osm_pbf-0.1.1.dist-info/RECORD
