Metadata-Version: 2.1
Name: esy-osm-pbf
Version: 0.1.1
Summary: Low-level Python library to interact with OSM PBF files
Author-email: Ontje Lünsdorf <ontje.luensdorf@dlr.de>
License: MIT License
Project-URL: homepage, https://gitlab.com/dlr-ve-esy/esy-osm-pbf
Keywords: OSM,OpenStreetMap,PBF,protobuf
Classifier: Development Status :: 5 - Production/Stable
Classifier: Environment :: Console
Classifier: Intended Audience :: Developers
Classifier: Intended Audience :: Education
Classifier: Intended Audience :: Science/Research
Classifier: License :: OSI Approved :: MIT License
Classifier: Natural Language :: English
Classifier: Operating System :: OS Independent
Classifier: Programming Language :: Python
Classifier: Programming Language :: Python :: 3
Classifier: Topic :: Scientific/Engineering
Requires-Python: >=3.5
License-File: LICENSE
Requires-Dist: protobuf>=3.20
Provides-Extra: dev
Requires-Dist: pdoc; extra == "dev"
